{"time":{"updated":"Sep 8, 2024 16:57:14 UTC","updatedISO":"2024-09-08T16:57:14+00:00","updateduk":"Sep 8, 2024 at 17:57 BST"},"disclaimer":"This data was produced from the CoinDesk Bitcoin Price Index (USD). Non-USD currency data converted using hourly conversion rate from openexchangerates.org","chartName":"Bitcoin","bpi":{"USD":{"code":"USD","symbol":"&#36;","rate":"53,919.416","description":"United States Dollar","rate_float":53919.416},"GBP":{"code":"GBP","symbol":"&pound;","rate":"41,061.145","description":"British Pound Sterling","rate_float":41061.1451},"EUR":{"code":"EUR","symbol":"&euro;","rate":"48,619.137","description":"Euro","rate_float":48619.1374},"CNY":{"code":"CNY","symbol":"&yen;","rate":"382,229.348","description":"Chinese Yuan","rate_float":382229.3483}}}