{"time":{"updated":"Sep 18, 2024 16:14:49 UTC","updatedISO":"2024-09-18T16:14:49+00:00","updateduk":"Sep 18, 2024 at 17:14 BST"},"disclaimer":"This data was produced from the CoinDesk Bitcoin Price Index (USD). Non-USD currency data converted using hourly conversion rate from openexchangerates.org","chartName":"Bitcoin","bpi":{"USD":{"code":"USD","symbol":"&#36;","rate":"59,499.647","description":"United States Dollar","rate_float":59499.6465},"GBP":{"code":"GBP","symbol":"&pound;","rate":"45,035.699","description":"British Pound Sterling","rate_float":45035.699},"EUR":{"code":"EUR","symbol":"&euro;","rate":"53,516.303","description":"Euro","rate_float":53516.3026},"CNY":{"code":"CNY","symbol":"&yen;","rate":"421,400.297","description":"Chinese Yuan","rate_float":421400.2967}}}