{"time":{"updated":"Jan 2, 2025 23:36:40 UTC","updatedISO":"2025-01-02T23:36:40+00:00","updateduk":"Jan 2, 2025 at 23:36 GMT"},"disclaimer":"This data was produced from the CoinDesk Bitcoin Price Index (USD). Non-USD currency data converted using hourly conversion rate from openexchangerates.org","chartName":"Bitcoin","bpi":{"USD":{"code":"USD","symbol":"&#36;","rate":"98,236.796","description":"United States Dollar","rate_float":98236.7956},"GBP":{"code":"GBP","symbol":"&pound;","rate":"78,341.88","description":"British Pound Sterling","rate_float":78341.8798},"EUR":{"code":"EUR","symbol":"&euro;","rate":"94,245.533","description":"Euro","rate_float":94245.5328},"CNY":{"code":"CNY","symbol":"&yen;","rate":"716,991.076","description":"Chinese Yuan","rate_float":716991.0763}}}