{"time":{"updated":"Feb 23, 2024 22:27:32 UTC","updatedISO":"2024-02-23T22:27:32+00:00","updateduk":"Feb 23, 2024 at 22:27 GMT"},"disclaimer":"This data was produced from the CoinDesk Bitcoin Price Index (USD). Non-USD currency data converted using hourly conversion rate from openexchangerates.org","chartName":"Bitcoin","bpi":{"USD":{"code":"USD","symbol":"&#36;","rate":"50,995.105","description":"United States Dollar","rate_float":50995.1046},"GBP":{"code":"GBP","symbol":"&pound;","rate":"40,242.379","description":"British Pound Sterling","rate_float":40242.3788},"EUR":{"code":"EUR","symbol":"&euro;","rate":"47,119.528","description":"Euro","rate_float":47119.5276},"CNY":{"code":"CNY","symbol":"&yen;","rate":"366,930.176","description":"Chinese Yuan","rate_float":366930.1755}}}