{"time":{"updated":"Nov 23, 2024 22:14:06 UTC","updatedISO":"2024-11-23T22:14:06+00:00","updateduk":"Nov 23, 2024 at 22:14 GMT"},"disclaimer":"This data was produced from the CoinDesk Bitcoin Price Index (USD). Non-USD currency data converted using hourly conversion rate from openexchangerates.org","chartName":"Bitcoin","bpi":{"USD":{"code":"USD","symbol":"&#36;","rate":"97,478.288","description":"United States Dollar","rate_float":97478.2876},"GBP":{"code":"GBP","symbol":"&pound;","rate":"77,792.84","description":"British Pound Sterling","rate_float":77792.8399},"EUR":{"code":"EUR","symbol":"&euro;","rate":"93,567.166","description":"Euro","rate_float":93567.1663},"CNY":{"code":"CNY","symbol":"&yen;","rate":"706,035.237","description":"Chinese Yuan","rate_float":706035.2374}}}