{"time":{"updated":"Jun 19, 2024 23:16:48 UTC","updatedISO":"2024-06-19T23:16:48+00:00","updateduk":"Jun 20, 2024 at 00:16 BST"},"disclaimer":"This data was produced from the CoinDesk Bitcoin Price Index (USD). Non-USD currency data converted using hourly conversion rate from openexchangerates.org","chartName":"Bitcoin","bpi":{"USD":{"code":"USD","symbol":"&#36;","rate":"64,969.532","description":"United States Dollar","rate_float":64969.5324},"GBP":{"code":"GBP","symbol":"&pound;","rate":"51,076.318","description":"British Pound Sterling","rate_float":51076.3177},"EUR":{"code":"EUR","symbol":"&euro;","rate":"60,459.283","description":"Euro","rate_float":60459.2825},"CNY":{"code":"CNY","symbol":"&yen;","rate":"471,529.376","description":"Chinese Yuan","rate_float":471529.3756}}}