{"time":{"updated":"Nov 11, 2024 18:49:52 UTC","updatedISO":"2024-11-11T18:49:52+00:00","updateduk":"Nov 11, 2024 at 18:49 GMT"},"disclaimer":"This data was produced from the CoinDesk Bitcoin Price Index (USD). Non-USD currency data converted using hourly conversion rate from openexchangerates.org","chartName":"Bitcoin","bpi":{"USD":{"code":"USD","symbol":"&#36;","rate":"85,250.76","description":"United States Dollar","rate_float":85250.7601},"GBP":{"code":"GBP","symbol":"&pound;","rate":"66,269.167","description":"British Pound Sterling","rate_float":66269.1669},"EUR":{"code":"EUR","symbol":"&euro;","rate":"80,053.703","description":"Euro","rate_float":80053.7033},"CNY":{"code":"CNY","symbol":"&yen;","rate":"615,075.709","description":"Chinese Yuan","rate_float":615075.7091}}}