{"time":{"updated":"Oct 9, 2024 17:59:56 UTC","updatedISO":"2024-10-09T17:59:56+00:00","updateduk":"Oct 9, 2024 at 18:59 BST"},"disclaimer":"This data was produced from the CoinDesk Bitcoin Price Index (USD). Non-USD currency data converted using hourly conversion rate from openexchangerates.org","chartName":"Bitcoin","bpi":{"USD":{"code":"USD","symbol":"&#36;","rate":"61,706.906","description":"United States Dollar","rate_float":61706.9058},"GBP":{"code":"GBP","symbol":"&pound;","rate":"47,217.261","description":"British Pound Sterling","rate_float":47217.2605},"EUR":{"code":"EUR","symbol":"&euro;","rate":"56,395.793","description":"Euro","rate_float":56395.7925},"CNY":{"code":"CNY","symbol":"&yen;","rate":"437,026.819","description":"Chinese Yuan","rate_float":437026.8193}}}