{"time":{"updated":"Apr 19, 2024 18:56:11 UTC","updatedISO":"2024-04-19T18:56:11+00:00","updateduk":"Apr 19, 2024 at 19:56 BST"},"disclaimer":"This data was produced from the CoinDesk Bitcoin Price Index (USD). Non-USD currency data converted using hourly conversion rate from openexchangerates.org","chartName":"Bitcoin","bpi":{"USD":{"code":"USD","symbol":"&#36;","rate":"64,396.962","description":"United States Dollar","rate_float":64396.9615},"GBP":{"code":"GBP","symbol":"&pound;","rate":"52,035.836","description":"British Pound Sterling","rate_float":52035.8359},"EUR":{"code":"EUR","symbol":"&euro;","rate":"60,434.681","description":"Euro","rate_float":60434.6808},"CNY":{"code":"CNY","symbol":"&yen;","rate":"466,243.661","description":"Chinese Yuan","rate_float":466243.6605}}}