{"time":{"updated":"Jun 7, 2024 06:53:30 UTC","updatedISO":"2024-06-07T06:53:30+00:00","updateduk":"Jun 7, 2024 at 07:53 BST"},"disclaimer":"This data was produced from the CoinDesk Bitcoin Price Index (USD). Non-USD currency data converted using hourly conversion rate from openexchangerates.org","chartName":"Bitcoin","bpi":{"USD":{"code":"USD","symbol":"&#36;","rate":"71,302.511","description":"United States Dollar","rate_float":71302.5106},"GBP":{"code":"GBP","symbol":"&pound;","rate":"55,772.039","description":"British Pound Sterling","rate_float":55772.0394},"EUR":{"code":"EUR","symbol":"&euro;","rate":"65,471.177","description":"Euro","rate_float":65471.1773},"CNY":{"code":"CNY","symbol":"&yen;","rate":"516,565.298","description":"Chinese Yuan","rate_float":516565.2983}}}