{"time":{"updated":"Jan 8, 2025 07:16:44 UTC","updatedISO":"2025-01-08T07:16:44+00:00","updateduk":"Jan 8, 2025 at 07:16 GMT"},"disclaimer":"This data was produced from the CoinDesk Bitcoin Price Index (USD). Non-USD currency data converted using hourly conversion rate from openexchangerates.org","chartName":"Bitcoin","bpi":{"USD":{"code":"USD","symbol":"&#36;","rate":"96,145.406","description":"United States Dollar","rate_float":96145.4055},"GBP":{"code":"GBP","symbol":"&pound;","rate":"76,683.172","description":"British Pound Sterling","rate_float":76683.1718},"EUR":{"code":"EUR","symbol":"&euro;","rate":"92,466.305","description":"Euro","rate_float":92466.3054},"CNY":{"code":"CNY","symbol":"&yen;","rate":"704,543.917","description":"Chinese Yuan","rate_float":704543.9167}}}