{"time":{"updated":"Jan 11, 2025 04:47:54 UTC","updatedISO":"2025-01-11T04:47:54+00:00","updateduk":"Jan 11, 2025 at 04:47 GMT"},"disclaimer":"This data was produced from the CoinDesk Bitcoin Price Index (USD). Non-USD currency data converted using hourly conversion rate from openexchangerates.org","chartName":"Bitcoin","bpi":{"USD":{"code":"USD","symbol":"&#36;","rate":"95,280.177","description":"United States Dollar","rate_float":95280.1773},"GBP":{"code":"GBP","symbol":"&pound;","rate":"75,993.087","description":"British Pound Sterling","rate_float":75993.0874},"EUR":{"code":"EUR","symbol":"&euro;","rate":"91,634.186","description":"Euro","rate_float":91634.186},"CNY":{"code":"CNY","symbol":"&yen;","rate":"698,203.611","description":"Chinese Yuan","rate_float":698203.6112}}}