{"time":{"updated":"Nov 30, 2024 07:16:33 UTC","updatedISO":"2024-11-30T07:16:33+00:00","updateduk":"Nov 30, 2024 at 07:16 GMT"},"disclaimer":"This data was produced from the CoinDesk Bitcoin Price Index (USD). Non-USD currency data converted using hourly conversion rate from openexchangerates.org","chartName":"Bitcoin","bpi":{"USD":{"code":"USD","symbol":"&#36;","rate":"96,756.062","description":"United States Dollar","rate_float":96756.0619},"GBP":{"code":"GBP","symbol":"&pound;","rate":"75,988.438","description":"British Pound Sterling","rate_float":75988.4376},"EUR":{"code":"EUR","symbol":"&euro;","rate":"91,453.056","description":"Euro","rate_float":91453.0557},"CNY":{"code":"CNY","symbol":"&yen;","rate":"700,678.374","description":"Chinese Yuan","rate_float":700678.3737}}}