{"time":{"updated":"May 14, 2024 14:38:22 UTC","updatedISO":"2024-05-14T14:38:22+00:00","updateduk":"May 14, 2024 at 15:38 BST"},"disclaimer":"This data was produced from the CoinDesk Bitcoin Price Index (USD). Non-USD currency data converted using hourly conversion rate from openexchangerates.org","chartName":"Bitcoin","bpi":{"USD":{"code":"USD","symbol":"&#36;","rate":"61,786.829","description":"United States Dollar","rate_float":61786.829},"GBP":{"code":"GBP","symbol":"&pound;","rate":"49,101.931","description":"British Pound Sterling","rate_float":49101.9312},"EUR":{"code":"EUR","symbol":"&euro;","rate":"57,108.578","description":"Euro","rate_float":57108.5775},"CNY":{"code":"CNY","symbol":"&yen;","rate":"446,922.67","description":"Chinese Yuan","rate_float":446922.6702}}}