{"time":{"updated":"Feb 2, 2024 14:40:43 UTC","updatedISO":"2024-02-02T14:40:43+00:00","updateduk":"Feb 2, 2024 at 14:40 GMT"},"disclaimer":"This data was produced from the CoinDesk Bitcoin Price Index (USD). Non-USD currency data converted using hourly conversion rate from openexchangerates.org","chartName":"Bitcoin","bpi":{"USD":{"code":"USD","symbol":"&#36;","rate":"42,997.893","description":"United States Dollar","rate_float":42997.8929},"GBP":{"code":"GBP","symbol":"&pound;","rate":"33,933.507","description":"British Pound Sterling","rate_float":33933.5071},"EUR":{"code":"EUR","symbol":"&euro;","rate":"39,787.025","description":"Euro","rate_float":39787.0252},"CNY":{"code":"CNY","symbol":"&yen;","rate":"305,921.408","description":"Chinese Yuan","rate_float":305921.4081}}}