{"time":{"updated":"Nov 6, 2024 09:58:50 UTC","updatedISO":"2024-11-06T09:58:50+00:00","updateduk":"Nov 6, 2024 at 09:58 GMT"},"disclaimer":"This data was produced from the CoinDesk Bitcoin Price Index (USD). Non-USD currency data converted using hourly conversion rate from openexchangerates.org","chartName":"Bitcoin","bpi":{"USD":{"code":"USD","symbol":"&#36;","rate":"73,879.176","description":"United States Dollar","rate_float":73879.1761},"GBP":{"code":"GBP","symbol":"&pound;","rate":"57,186.324","description":"British Pound Sterling","rate_float":57186.324},"EUR":{"code":"EUR","symbol":"&euro;","rate":"68,577.385","description":"Euro","rate_float":68577.3848},"CNY":{"code":"CNY","symbol":"&yen;","rate":"528,797.591","description":"Chinese Yuan","rate_float":528797.5911}}}