{"time":{"updated":"Mar 20, 2024 07:35:16 UTC","updatedISO":"2024-03-20T07:35:16+00:00","updateduk":"Mar 20, 2024 at 07:35 GMT"},"disclaimer":"This data was produced from the CoinDesk Bitcoin Price Index (USD). Non-USD currency data converted using hourly conversion rate from openexchangerates.org","chartName":"Bitcoin","bpi":{"USD":{"code":"USD","symbol":"&#36;","rate":"62,706.301","description":"United States Dollar","rate_float":62706.301},"GBP":{"code":"GBP","symbol":"&pound;","rate":"49,320.262","description":"British Pound Sterling","rate_float":49320.2615},"EUR":{"code":"EUR","symbol":"&euro;","rate":"57,685.596","description":"Euro","rate_float":57685.5956},"CNY":{"code":"CNY","symbol":"&yen;","rate":"451,441.473","description":"Chinese Yuan","rate_float":451441.4729}}}