{"time":{"updated":"Aug 4, 2024 03:29:02 UTC","updatedISO":"2024-08-04T03:29:02+00:00","updateduk":"Aug 4, 2024 at 04:29 BST"},"disclaimer":"This data was produced from the CoinDesk Bitcoin Price Index (USD). Non-USD currency data converted using hourly conversion rate from openexchangerates.org","chartName":"Bitcoin","bpi":{"USD":{"code":"USD","symbol":"&#36;","rate":"60,901.179","description":"United States Dollar","rate_float":60901.1787},"GBP":{"code":"GBP","symbol":"&pound;","rate":"47,556.756","description":"British Pound Sterling","rate_float":47556.756},"EUR":{"code":"EUR","symbol":"&euro;","rate":"55,788.22","description":"Euro","rate_float":55788.2202},"CNY":{"code":"CNY","symbol":"&yen;","rate":"436,003.719","description":"Chinese Yuan","rate_float":436003.7185}}}