{"time":{"updated":"Oct 30, 2024 11:43:44 UTC","updatedISO":"2024-10-30T11:43:44+00:00","updateduk":"Oct 30, 2024 at 11:43 GMT"},"disclaimer":"This data was produced from the CoinDesk Bitcoin Price Index (USD). Non-USD currency data converted using hourly conversion rate from openexchangerates.org","chartName":"Bitcoin","bpi":{"USD":{"code":"USD","symbol":"&#36;","rate":"72,189.637","description":"United States Dollar","rate_float":72189.637},"GBP":{"code":"GBP","symbol":"&pound;","rate":"55,634.965","description":"British Pound Sterling","rate_float":55634.9651},"EUR":{"code":"EUR","symbol":"&euro;","rate":"66,630.818","description":"Euro","rate_float":66630.8184},"CNY":{"code":"CNY","symbol":"&yen;","rate":"514,372.821","description":"Chinese Yuan","rate_float":514372.8205}}}