{"time":{"updated":"Aug 24, 2024 07:01:12 UTC","updatedISO":"2024-08-24T07:01:12+00:00","updateduk":"Aug 24, 2024 at 08:01 BST"},"disclaimer":"This data was produced from the CoinDesk Bitcoin Price Index (USD). Non-USD currency data converted using hourly conversion rate from openexchangerates.org","chartName":"Bitcoin","bpi":{"USD":{"code":"USD","symbol":"&#36;","rate":"64,132.196","description":"United States Dollar","rate_float":64132.1958},"GBP":{"code":"GBP","symbol":"&pound;","rate":"48,540.889","description":"British Pound Sterling","rate_float":48540.8894},"EUR":{"code":"EUR","symbol":"&euro;","rate":"57,247.605","description":"Euro","rate_float":57247.6046},"CNY":{"code":"CNY","symbol":"&yen;","rate":"456,820.044","description":"Chinese Yuan","rate_float":456820.0442}}}