{"time":{"updated":"Jun 5, 2024 18:43:50 UTC","updatedISO":"2024-06-05T18:43:50+00:00","updateduk":"Jun 5, 2024 at 19:43 BST"},"disclaimer":"This data was produced from the CoinDesk Bitcoin Price Index (USD). Non-USD currency data converted using hourly conversion rate from openexchangerates.org","chartName":"Bitcoin","bpi":{"USD":{"code":"USD","symbol":"&#36;","rate":"71,027.898","description":"United States Dollar","rate_float":71027.8978},"GBP":{"code":"GBP","symbol":"&pound;","rate":"55,563.491","description":"British Pound Sterling","rate_float":55563.4908},"EUR":{"code":"EUR","symbol":"&euro;","rate":"65,359.659","description":"Euro","rate_float":65359.6585},"CNY":{"code":"CNY","symbol":"&yen;","rate":"514,774.689","description":"Chinese Yuan","rate_float":514774.6894}}}