{"time":{"updated":"Jun 11, 2024 11:21:24 UTC","updatedISO":"2024-06-11T11:21:24+00:00","updateduk":"Jun 11, 2024 at 12:21 BST"},"disclaimer":"This data was produced from the CoinDesk Bitcoin Price Index (USD). Non-USD currency data converted using hourly conversion rate from openexchangerates.org","chartName":"Bitcoin","bpi":{"USD":{"code":"USD","symbol":"&#36;","rate":"67,133.522","description":"United States Dollar","rate_float":67133.5223},"GBP":{"code":"GBP","symbol":"&pound;","rate":"52,684.777","description":"British Pound Sterling","rate_float":52684.7771},"EUR":{"code":"EUR","symbol":"&euro;","rate":"62,499.832","description":"Euro","rate_float":62499.8323},"CNY":{"code":"CNY","symbol":"&yen;","rate":"477,245.497","description":"Chinese Yuan","rate_float":477245.4968}}}