{"time":{"updated":"Dec 30, 2024 20:53:24 UTC","updatedISO":"2024-12-30T20:53:24+00:00","updateduk":"Dec 30, 2024 at 20:53 GMT"},"disclaimer":"This data was produced from the CoinDesk Bitcoin Price Index (USD). Non-USD currency data converted using hourly conversion rate from openexchangerates.org","chartName":"Bitcoin","bpi":{"USD":{"code":"USD","symbol":"&#36;","rate":"94,698.919","description":"United States Dollar","rate_float":94698.9194},"GBP":{"code":"GBP","symbol":"&pound;","rate":"75,520.494","description":"British Pound Sterling","rate_float":75520.4943},"EUR":{"code":"EUR","symbol":"&euro;","rate":"90,851.397","description":"Euro","rate_float":90851.397},"CNY":{"code":"CNY","symbol":"&yen;","rate":"691,169.533","description":"Chinese Yuan","rate_float":691169.5334}}}