{"time":{"updated":"Aug 23, 2024 21:30:01 UTC","updatedISO":"2024-08-23T21:30:01+00:00","updateduk":"Aug 23, 2024 at 22:30 BST"},"disclaimer":"This data was produced from the CoinDesk Bitcoin Price Index (USD). Non-USD currency data converted using hourly conversion rate from openexchangerates.org","chartName":"Bitcoin","bpi":{"USD":{"code":"USD","symbol":"&#36;","rate":"64,299.1","description":"United States Dollar","rate_float":64299.1001},"GBP":{"code":"GBP","symbol":"&pound;","rate":"48,654.55","description":"British Pound Sterling","rate_float":48654.5504},"EUR":{"code":"EUR","symbol":"&euro;","rate":"57,441.537","description":"Euro","rate_float":57441.5368},"CNY":{"code":"CNY","symbol":"&yen;","rate":"458,008.92","description":"Chinese Yuan","rate_float":458008.92}}}