{"time":{"updated":"Jan 30, 2024 07:28:06 UTC","updatedISO":"2024-01-30T07:28:06+00:00","updateduk":"Jan 30, 2024 at 07:28 GMT"},"disclaimer":"This data was produced from the CoinDesk Bitcoin Price Index (USD). Non-USD currency data converted using hourly conversion rate from openexchangerates.org","chartName":"Bitcoin","bpi":{"USD":{"code":"USD","symbol":"&#36;","rate":"43,466.868","description":"United States Dollar","rate_float":43466.8684},"GBP":{"code":"GBP","symbol":"&pound;","rate":"34,212.424","description":"British Pound Sterling","rate_float":34212.4243},"EUR":{"code":"EUR","symbol":"&euro;","rate":"40,163.213","description":"Euro","rate_float":40163.2125},"CNY":{"code":"CNY","symbol":"&yen;","rate":"308,462.631","description":"Chinese Yuan","rate_float":308462.6312}}}