{"time":{"updated":"Mar 26, 2024 16:57:04 UTC","updatedISO":"2024-03-26T16:57:04+00:00","updateduk":"Mar 26, 2024 at 16:57 GMT"},"disclaimer":"This data was produced from the CoinDesk Bitcoin Price Index (USD). Non-USD currency data converted using hourly conversion rate from openexchangerates.org","chartName":"Bitcoin","bpi":{"USD":{"code":"USD","symbol":"&#36;","rate":"69,648.33","description":"United States Dollar","rate_float":69648.3297},"GBP":{"code":"GBP","symbol":"&pound;","rate":"55,151.587","description":"British Pound Sterling","rate_float":55151.5871},"EUR":{"code":"EUR","symbol":"&euro;","rate":"64,319.049","description":"Euro","rate_float":64319.0485},"CNY":{"code":"CNY","symbol":"&yen;","rate":"502,749.504","description":"Chinese Yuan","rate_float":502749.5035}}}