{"time":{"updated":"Jan 31, 2024 09:32:50 UTC","updatedISO":"2024-01-31T09:32:50+00:00","updateduk":"Jan 31, 2024 at 09:32 GMT"},"disclaimer":"This data was produced from the CoinDesk Bitcoin Price Index (USD). Non-USD currency data converted using hourly conversion rate from openexchangerates.org","chartName":"Bitcoin","bpi":{"USD":{"code":"USD","symbol":"&#36;","rate":"42,792.019","description":"United States Dollar","rate_float":42792.0193},"GBP":{"code":"GBP","symbol":"&pound;","rate":"33,716.046","description":"British Pound Sterling","rate_float":33716.046},"EUR":{"code":"EUR","symbol":"&euro;","rate":"39,551.679","description":"Euro","rate_float":39551.6793},"CNY":{"code":"CNY","symbol":"&yen;","rate":"303,528.072","description":"Chinese Yuan","rate_float":303528.0724}}}