{"time":{"updated":"May 10, 2024 02:52:44 UTC","updatedISO":"2024-05-10T02:52:44+00:00","updateduk":"May 10, 2024 at 03:52 BST"},"disclaimer":"This data was produced from the CoinDesk Bitcoin Price Index (USD). Non-USD currency data converted using hourly conversion rate from openexchangerates.org","chartName":"Bitcoin","bpi":{"USD":{"code":"USD","symbol":"&#36;","rate":"62,819.319","description":"United States Dollar","rate_float":62819.319},"GBP":{"code":"GBP","symbol":"&pound;","rate":"50,186.291","description":"British Pound Sterling","rate_float":50186.2912},"EUR":{"code":"EUR","symbol":"&euro;","rate":"58,294.381","description":"Euro","rate_float":58294.3807},"CNY":{"code":"CNY","symbol":"&yen;","rate":"453,863.298","description":"Chinese Yuan","rate_float":453863.2981}}}