{"time":{"updated":"Aug 11, 2024 19:51:37 UTC","updatedISO":"2024-08-11T19:51:37+00:00","updateduk":"Aug 11, 2024 at 20:51 BST"},"disclaimer":"This data was produced from the CoinDesk Bitcoin Price Index (USD). Non-USD currency data converted using hourly conversion rate from openexchangerates.org","chartName":"Bitcoin","bpi":{"USD":{"code":"USD","symbol":"&#36;","rate":"59,900.355","description":"United States Dollar","rate_float":59900.3553},"GBP":{"code":"GBP","symbol":"&pound;","rate":"46,953.073","description":"British Pound Sterling","rate_float":46953.0732},"EUR":{"code":"EUR","symbol":"&euro;","rate":"54,826.196","description":"Euro","rate_float":54826.1962},"CNY":{"code":"CNY","symbol":"&yen;","rate":"429,287.877","description":"Chinese Yuan","rate_float":429287.8765}}}