{"time":{"updated":"Jun 24, 2024 21:49:44 UTC","updatedISO":"2024-06-24T21:49:44+00:00","updateduk":"Jun 24, 2024 at 22:49 BST"},"disclaimer":"This data was produced from the CoinDesk Bitcoin Price Index (USD). Non-USD currency data converted using hourly conversion rate from openexchangerates.org","chartName":"Bitcoin","bpi":{"USD":{"code":"USD","symbol":"&#36;","rate":"59,909.026","description":"United States Dollar","rate_float":59909.0258},"GBP":{"code":"GBP","symbol":"&pound;","rate":"47,224.488","description":"British Pound Sterling","rate_float":47224.4878},"EUR":{"code":"EUR","symbol":"&euro;","rate":"55,810.35","description":"Euro","rate_float":55810.3498},"CNY":{"code":"CNY","symbol":"&yen;","rate":"434,877.821","description":"Chinese Yuan","rate_float":434877.8212}}}