{"time":{"updated":"Apr 1, 2022 22:09:00 UTC","updatedISO":"2022-04-01T22:09:00+00:00","updateduk":"Apr 1, 2022 at 23:09 BST"},"disclaimer":"This data was produced from the CoinDesk Bitcoin Price Index (USD). Non-USD currency data converted using hourly conversion rate from openexchangerates.org","chartName":"Bitcoin","bpi":{"USD":{"code":"USD","symbol":"&#36;","rate":"46,407.3592","description":"United States Dollar","rate_float":46407.3592},"GBP":{"code":"GBP","symbol":"&pound;","rate":"35,425.3361","description":"British Pound Sterling","rate_float":35425.3361},"EUR":{"code":"EUR","symbol":"&euro;","rate":"42,015.1347","description":"Euro","rate_float":42015.1347},"CNY":{"code":"CNY","symbol":"&yen;","rate":"40,202.5000","description":"Chinese Yuan","rate_float":40202.5}}}