{"time":{"updated":"May 26, 2024 13:56:41 UTC","updatedISO":"2024-05-26T13:56:41+00:00","updateduk":"May 26, 2024 at 14:56 BST"},"disclaimer":"This data was produced from the CoinDesk Bitcoin Price Index (USD). Non-USD currency data converted using hourly conversion rate from openexchangerates.org","chartName":"Bitcoin","bpi":{"USD":{"code":"USD","symbol":"&#36;","rate":"69,052.781","description":"United States Dollar","rate_float":69052.7807},"GBP":{"code":"GBP","symbol":"&pound;","rate":"54,524.697","description":"British Pound Sterling","rate_float":54524.6971},"EUR":{"code":"EUR","symbol":"&euro;","rate":"63,654.856","description":"Euro","rate_float":63654.8558},"CNY":{"code":"CNY","symbol":"&yen;","rate":"491,041.229","description":"Chinese Yuan","rate_float":491041.229}}}