{"time":{"updated":"Feb 16, 2024 14:09:47 UTC","updatedISO":"2024-02-16T14:09:47+00:00","updateduk":"Feb 16, 2024 at 14:09 GMT"},"disclaimer":"This data was produced from the CoinDesk Bitcoin Price Index (USD). Non-USD currency data converted using hourly conversion rate from openexchangerates.org","chartName":"Bitcoin","bpi":{"USD":{"code":"USD","symbol":"&#36;","rate":"52,396.099","description":"United States Dollar","rate_float":52396.0994},"GBP":{"code":"GBP","symbol":"&pound;","rate":"41,693.253","description":"British Pound Sterling","rate_float":41693.253},"EUR":{"code":"EUR","symbol":"&euro;","rate":"48,755.409","description":"Euro","rate_float":48755.4088},"CNY":{"code":"CNY","symbol":"&yen;","rate":"373,089.936","description":"Chinese Yuan","rate_float":373089.9364}}}