{"time":{"updated":"Apr 9, 2024 23:48:36 UTC","updatedISO":"2024-04-09T23:48:36+00:00","updateduk":"Apr 10, 2024 at 00:48 BST"},"disclaimer":"This data was produced from the CoinDesk Bitcoin Price Index (USD). Non-USD currency data converted using hourly conversion rate from openexchangerates.org","chartName":"Bitcoin","bpi":{"USD":{"code":"USD","symbol":"&#36;","rate":"69,299.952","description":"United States Dollar","rate_float":69299.9519},"GBP":{"code":"GBP","symbol":"&pound;","rate":"54,669.208","description":"British Pound Sterling","rate_float":54669.2075},"EUR":{"code":"EUR","symbol":"&euro;","rate":"63,820.058","description":"Euro","rate_float":63820.0582},"CNY":{"code":"CNY","symbol":"&yen;","rate":"501,184.182","description":"Chinese Yuan","rate_float":501184.1822}}}