{"time":{"updated":"Jul 6, 2023 11:08:00 UTC","updatedISO":"2023-07-06T11:08:00+00:00","updateduk":"Jul 6, 2023 at 12:08 BST"},"disclaimer":"This data was produced from the CoinDesk Bitcoin Price Index (USD). Non-USD currency data converted using hourly conversion rate from openexchangerates.org","chartName":"Bitcoin","bpi":{"USD":{"code":"USD","symbol":"&#36;","rate":"31,166.9082","description":"United States Dollar","rate_float":31166.9082},"GBP":{"code":"GBP","symbol":"&pound;","rate":"26,042.8192","description":"British Pound Sterling","rate_float":26042.8192},"EUR":{"code":"EUR","symbol":"&euro;","rate":"30,361.1190","description":"Euro","rate_float":30361.119},"CNY":{"code":"CNY","symbol":"&yen;","rate":"40,202.5000","description":"Chinese Yuan","rate_float":40202.5}}}