{"time":{"updated":"Oct 8, 2024 21:41:15 UTC","updatedISO":"2024-10-08T21:41:15+00:00","updateduk":"Oct 8, 2024 at 22:41 BST"},"disclaimer":"This data was produced from the CoinDesk Bitcoin Price Index (USD). Non-USD currency data converted using hourly conversion rate from openexchangerates.org","chartName":"Bitcoin","bpi":{"USD":{"code":"USD","symbol":"&#36;","rate":"62,446.088","description":"United States Dollar","rate_float":62446.0875},"GBP":{"code":"GBP","symbol":"&pound;","rate":"47,653.296","description":"British Pound Sterling","rate_float":47653.2963},"EUR":{"code":"EUR","symbol":"&euro;","rate":"56,866.904","description":"Euro","rate_float":56866.9043},"CNY":{"code":"CNY","symbol":"&yen;","rate":"440,760.722","description":"Chinese Yuan","rate_float":440760.7217}}}