{"time":{"updated":"Jun 27, 2024 14:42:06 UTC","updatedISO":"2024-06-27T14:42:06+00:00","updateduk":"Jun 27, 2024 at 15:42 BST"},"disclaimer":"This data was produced from the CoinDesk Bitcoin Price Index (USD). Non-USD currency data converted using hourly conversion rate from openexchangerates.org","chartName":"Bitcoin","bpi":{"USD":{"code":"USD","symbol":"&#36;","rate":"62,010.959","description":"United States Dollar","rate_float":62010.9588},"GBP":{"code":"GBP","symbol":"&pound;","rate":"48,970.054","description":"British Pound Sterling","rate_float":48970.0541},"EUR":{"code":"EUR","symbol":"&euro;","rate":"57,843.76","description":"Euro","rate_float":57843.7603},"CNY":{"code":"CNY","symbol":"&yen;","rate":"450,670.844","description":"Chinese Yuan","rate_float":450670.844}}}