{"time":{"updated":"Apr 9, 2024 21:00:02 UTC","updatedISO":"2024-04-09T21:00:02+00:00","updateduk":"Apr 9, 2024 at 22:00 BST"},"disclaimer":"This data was produced from the CoinDesk Bitcoin Price Index (USD). Non-USD currency data converted using hourly conversion rate from openexchangerates.org","chartName":"Bitcoin","bpi":{"USD":{"code":"USD","symbol":"&#36;","rate":"69,221.962","description":"United States Dollar","rate_float":69221.9624},"GBP":{"code":"GBP","symbol":"&pound;","rate":"54,611.698","description":"British Pound Sterling","rate_float":54611.6981},"EUR":{"code":"EUR","symbol":"&euro;","rate":"63,760.28","description":"Euro","rate_float":63760.2803},"CNY":{"code":"CNY","symbol":"&yen;","rate":"500,640.921","description":"Chinese Yuan","rate_float":500640.9206}}}