{"time":{"updated":"Oct 4, 2024 06:20:34 UTC","updatedISO":"2024-10-04T06:20:34+00:00","updateduk":"Oct 4, 2024 at 07:20 BST"},"disclaimer":"This data was produced from the CoinDesk Bitcoin Price Index (USD). Non-USD currency data converted using hourly conversion rate from openexchangerates.org","chartName":"Bitcoin","bpi":{"USD":{"code":"USD","symbol":"&#36;","rate":"61,211.069","description":"United States Dollar","rate_float":61211.0688},"GBP":{"code":"GBP","symbol":"&pound;","rate":"46,593.437","description":"British Pound Sterling","rate_float":46593.4371},"EUR":{"code":"EUR","symbol":"&euro;","rate":"55,478.897","description":"Euro","rate_float":55478.8971},"CNY":{"code":"CNY","symbol":"&yen;","rate":"431,507.43","description":"Chinese Yuan","rate_float":431507.4296}}}