{"time":{"updated":"Jul 31, 2024 20:24:07 UTC","updatedISO":"2024-07-31T20:24:07+00:00","updateduk":"Jul 31, 2024 at 21:24 BST"},"disclaimer":"This data was produced from the CoinDesk Bitcoin Price Index (USD). Non-USD currency data converted using hourly conversion rate from openexchangerates.org","chartName":"Bitcoin","bpi":{"USD":{"code":"USD","symbol":"&#36;","rate":"64,860.186","description":"United States Dollar","rate_float":64860.186},"GBP":{"code":"GBP","symbol":"&pound;","rate":"50,457.593","description":"British Pound Sterling","rate_float":50457.5925},"EUR":{"code":"EUR","symbol":"&euro;","rate":"59,931.331","description":"Euro","rate_float":59931.3308},"CNY":{"code":"CNY","symbol":"&yen;","rate":"468,245.141","description":"Chinese Yuan","rate_float":468245.1409}}}