{"time":{"updated":"Nov 28, 2024 09:43:29 UTC","updatedISO":"2024-11-28T09:43:29+00:00","updateduk":"Nov 28, 2024 at 09:43 GMT"},"disclaimer":"This data was produced from the CoinDesk Bitcoin Price Index (USD). Non-USD currency data converted using hourly conversion rate from openexchangerates.org","chartName":"Bitcoin","bpi":{"USD":{"code":"USD","symbol":"&#36;","rate":"95,341.612","description":"United States Dollar","rate_float":95341.612},"GBP":{"code":"GBP","symbol":"&pound;","rate":"75,369.356","description":"British Pound Sterling","rate_float":75369.3558},"EUR":{"code":"EUR","symbol":"&euro;","rate":"90,417.122","description":"Euro","rate_float":90417.1224},"CNY":{"code":"CNY","symbol":"&yen;","rate":"691,264.824","description":"Chinese Yuan","rate_float":691264.8235}}}