{"time":{"updated":"May 15, 2024 06:56:17 UTC","updatedISO":"2024-05-15T06:56:17+00:00","updateduk":"May 15, 2024 at 07:56 BST"},"disclaimer":"This data was produced from the CoinDesk Bitcoin Price Index (USD). Non-USD currency data converted using hourly conversion rate from openexchangerates.org","chartName":"Bitcoin","bpi":{"USD":{"code":"USD","symbol":"&#36;","rate":"61,975.98","description":"United States Dollar","rate_float":61975.9802},"GBP":{"code":"GBP","symbol":"&pound;","rate":"49,193.496","description":"British Pound Sterling","rate_float":49193.4963},"EUR":{"code":"EUR","symbol":"&euro;","rate":"57,240.706","description":"Euro","rate_float":57240.7055},"CNY":{"code":"CNY","symbol":"&yen;","rate":"447,677.296","description":"Chinese Yuan","rate_float":447677.2956}}}