{"time":{"updated":"Dec 14, 2024 11:34:45 UTC","updatedISO":"2024-12-14T11:34:45+00:00","updateduk":"Dec 14, 2024 at 11:34 GMT"},"disclaimer":"This data was produced from the CoinDesk Bitcoin Price Index (USD). Non-USD currency data converted using hourly conversion rate from openexchangerates.org","chartName":"Bitcoin","bpi":{"USD":{"code":"USD","symbol":"&#36;","rate":"101,874.412","description":"United States Dollar","rate_float":101874.4123},"GBP":{"code":"GBP","symbol":"&pound;","rate":"79,713.977","description":"British Pound Sterling","rate_float":79713.977},"EUR":{"code":"EUR","symbol":"&euro;","rate":"96,734.848","description":"Euro","rate_float":96734.8482},"CNY":{"code":"CNY","symbol":"&yen;","rate":"738,558.927","description":"Chinese Yuan","rate_float":738558.9269}}}