{"time":{"updated":"Apr 7, 2023 22:55:00 UTC","updatedISO":"2023-04-07T22:55:00+00:00","updateduk":"Apr 7, 2023 at 23:55 BST"},"disclaimer":"This data was produced from the CoinDesk Bitcoin Price Index (USD). Non-USD currency data converted using hourly conversion rate from openexchangerates.org","chartName":"Bitcoin","bpi":{"USD":{"code":"USD","symbol":"&#36;","rate":"27,928.8494","description":"United States Dollar","rate_float":27928.8494},"GBP":{"code":"GBP","symbol":"&pound;","rate":"23,337.1231","description":"British Pound Sterling","rate_float":23337.1231},"EUR":{"code":"EUR","symbol":"&euro;","rate":"27,206.7769","description":"Euro","rate_float":27206.7769},"CNY":{"code":"CNY","symbol":"&yen;","rate":"40,202.5000","description":"Chinese Yuan","rate_float":40202.5}}}