{"time":{"updated":"Mar 26, 2024 07:03:44 UTC","updatedISO":"2024-03-26T07:03:44+00:00","updateduk":"Mar 26, 2024 at 07:03 GMT"},"disclaimer":"This data was produced from the CoinDesk Bitcoin Price Index (USD). Non-USD currency data converted using hourly conversion rate from openexchangerates.org","chartName":"Bitcoin","bpi":{"USD":{"code":"USD","symbol":"&#36;","rate":"70,828.01","description":"United States Dollar","rate_float":70828.0103},"GBP":{"code":"GBP","symbol":"&pound;","rate":"56,009.232","description":"British Pound Sterling","rate_float":56009.2323},"EUR":{"code":"EUR","symbol":"&euro;","rate":"65,296.272","description":"Euro","rate_float":65296.2719},"CNY":{"code":"CNY","symbol":"&yen;","rate":"511,250.744","description":"Chinese Yuan","rate_float":511250.7441}}}