{"time":{"updated":"Jun 7, 2024 15:47:20 UTC","updatedISO":"2024-06-07T15:47:20+00:00","updateduk":"Jun 7, 2024 at 16:47 BST"},"disclaimer":"This data was produced from the CoinDesk Bitcoin Price Index (USD). Non-USD currency data converted using hourly conversion rate from openexchangerates.org","chartName":"Bitcoin","bpi":{"USD":{"code":"USD","symbol":"&#36;","rate":"70,940.384","description":"United States Dollar","rate_float":70940.384},"GBP":{"code":"GBP","symbol":"&pound;","rate":"55,761.27","description":"British Pound Sterling","rate_float":55761.2701},"EUR":{"code":"EUR","symbol":"&euro;","rate":"65,609.782","description":"Euro","rate_float":65609.7817},"CNY":{"code":"CNY","symbol":"&yen;","rate":"514,076.587","description":"Chinese Yuan","rate_float":514076.5869}}}