{"time":{"updated":"Apr 30, 2024 15:11:59 UTC","updatedISO":"2024-04-30T15:11:59+00:00","updateduk":"Apr 30, 2024 at 16:11 BST"},"disclaimer":"This data was produced from the CoinDesk Bitcoin Price Index (USD). Non-USD currency data converted using hourly conversion rate from openexchangerates.org","chartName":"Bitcoin","bpi":{"USD":{"code":"USD","symbol":"&#36;","rate":"60,907.976","description":"United States Dollar","rate_float":60907.9757},"GBP":{"code":"GBP","symbol":"&pound;","rate":"48,646.774","description":"British Pound Sterling","rate_float":48646.7739},"EUR":{"code":"EUR","symbol":"&euro;","rate":"56,893.348","description":"Euro","rate_float":56893.3483},"CNY":{"code":"CNY","symbol":"&yen;","rate":"441,119.923","description":"Chinese Yuan","rate_float":441119.9234}}}