{"time":{"updated":"Feb 12, 2024 08:58:22 UTC","updatedISO":"2024-02-12T08:58:22+00:00","updateduk":"Feb 12, 2024 at 08:58 GMT"},"disclaimer":"This data was produced from the CoinDesk Bitcoin Price Index (USD). Non-USD currency data converted using hourly conversion rate from openexchangerates.org","chartName":"Bitcoin","bpi":{"USD":{"code":"USD","symbol":"&#36;","rate":"48,166.771","description":"United States Dollar","rate_float":48166.7707},"GBP":{"code":"GBP","symbol":"&pound;","rate":"38,086.14","description":"British Pound Sterling","rate_float":38086.14},"EUR":{"code":"EUR","symbol":"&euro;","rate":"44,586.535","description":"Euro","rate_float":44586.5347},"CNY":{"code":"CNY","symbol":"&yen;","rate":"346,463.582","description":"Chinese Yuan","rate_float":346463.5819}}}