{"time":{"updated":"Apr 19, 2024 03:11:23 UTC","updatedISO":"2024-04-19T03:11:23+00:00","updateduk":"Apr 19, 2024 at 04:11 BST"},"disclaimer":"This data was produced from the CoinDesk Bitcoin Price Index (USD). Non-USD currency data converted using hourly conversion rate from openexchangerates.org","chartName":"Bitcoin","bpi":{"USD":{"code":"USD","symbol":"&#36;","rate":"61,498.504","description":"United States Dollar","rate_float":61498.504},"GBP":{"code":"GBP","symbol":"&pound;","rate":"49,591.287","description":"British Pound Sterling","rate_float":49591.2867},"EUR":{"code":"EUR","symbol":"&euro;","rate":"57,914.802","description":"Euro","rate_float":57914.8017},"CNY":{"code":"CNY","symbol":"&yen;","rate":"445,341.417","description":"Chinese Yuan","rate_float":445341.4168}}}