{"time":{"updated":"Apr 28, 2024 06:29:14 UTC","updatedISO":"2024-04-28T06:29:14+00:00","updateduk":"Apr 28, 2024 at 07:29 BST"},"disclaimer":"This data was produced from the CoinDesk Bitcoin Price Index (USD). Non-USD currency data converted using hourly conversion rate from openexchangerates.org","chartName":"Bitcoin","bpi":{"USD":{"code":"USD","symbol":"&#36;","rate":"63,827.511","description":"United States Dollar","rate_float":63827.5107},"GBP":{"code":"GBP","symbol":"&pound;","rate":"51,111.092","description":"British Pound Sterling","rate_float":51111.0919},"EUR":{"code":"EUR","symbol":"&euro;","rate":"59,671.382","description":"Euro","rate_float":59671.3823},"CNY":{"code":"CNY","symbol":"&yen;","rate":"462,468.612","description":"Chinese Yuan","rate_float":462468.6115}}}