{"time":{"updated":"Jan 7, 2025 06:23:32 UTC","updatedISO":"2025-01-07T06:23:32+00:00","updateduk":"Jan 7, 2025 at 06:23 GMT"},"disclaimer":"This data was produced from the CoinDesk Bitcoin Price Index (USD). Non-USD currency data converted using hourly conversion rate from openexchangerates.org","chartName":"Bitcoin","bpi":{"USD":{"code":"USD","symbol":"&#36;","rate":"101,942.436","description":"United States Dollar","rate_float":101942.4357},"GBP":{"code":"GBP","symbol":"&pound;","rate":"81,297.054","description":"British Pound Sterling","rate_float":81297.0537},"EUR":{"code":"EUR","symbol":"&euro;","rate":"97,800.617","description":"Euro","rate_float":97800.6165},"CNY":{"code":"CNY","symbol":"&yen;","rate":"744,037.062","description":"Chinese Yuan","rate_float":744037.0615}}}