{"time":{"updated":"Jul 18, 2024 10:51:32 UTC","updatedISO":"2024-07-18T10:51:32+00:00","updateduk":"Jul 18, 2024 at 11:51 BST"},"disclaimer":"This data was produced from the CoinDesk Bitcoin Price Index (USD). Non-USD currency data converted using hourly conversion rate from openexchangerates.org","chartName":"Bitcoin","bpi":{"USD":{"code":"USD","symbol":"&#36;","rate":"64,557.313","description":"United States Dollar","rate_float":64557.3129},"GBP":{"code":"GBP","symbol":"&pound;","rate":"49,700.739","description":"British Pound Sterling","rate_float":49700.7385},"EUR":{"code":"EUR","symbol":"&euro;","rate":"59,050.574","description":"Euro","rate_float":59050.5741},"CNY":{"code":"CNY","symbol":"&yen;","rate":"468,615.079","description":"Chinese Yuan","rate_float":468615.0786}}}