{"time":{"updated":"Jan 23, 2025 05:55:08 UTC","updatedISO":"2025-01-23T05:55:08+00:00","updateduk":"Jan 23, 2025 at 05:55 GMT"},"disclaimer":"This data was produced from the CoinDesk Bitcoin Price Index (USD). Non-USD currency data converted using hourly conversion rate from openexchangerates.org","chartName":"Bitcoin","bpi":{"USD":{"code":"USD","symbol":"&#36;","rate":"102,512.382","description":"United States Dollar","rate_float":102512.3823},"GBP":{"code":"GBP","symbol":"&pound;","rate":"81,761.313","description":"British Pound Sterling","rate_float":81761.3133},"EUR":{"code":"EUR","symbol":"&euro;","rate":"98,589.644","description":"Euro","rate_float":98589.6435},"CNY":{"code":"CNY","symbol":"&yen;","rate":"751,200.486","description":"Chinese Yuan","rate_float":751200.4864}}}