{"time":{"updated":"Jun 19, 2022 17:37:00 UTC","updatedISO":"2022-06-19T17:37:00+00:00","updateduk":"Jun 19, 2022 at 18:37 BST"},"disclaimer":"This data was produced from the CoinDesk Bitcoin Price Index (USD). Non-USD currency data converted using hourly conversion rate from openexchangerates.org","chartName":"Bitcoin","bpi":{"USD":{"code":"USD","symbol":"&#36;","rate":"19,444.9955","description":"United States Dollar","rate_float":19444.9955},"GBP":{"code":"GBP","symbol":"&pound;","rate":"15,787.7613","description":"British Pound Sterling","rate_float":15787.7613},"EUR":{"code":"EUR","symbol":"&euro;","rate":"18,483.8294","description":"Euro","rate_float":18483.8294},"CNY":{"code":"CNY","symbol":"&yen;","rate":"40,202.5000","description":"Chinese Yuan","rate_float":40202.5}}}