{"time":{"updated":"Apr 18, 2024 22:44:51 UTC","updatedISO":"2024-04-18T22:44:51+00:00","updateduk":"Apr 18, 2024 at 23:44 BST"},"disclaimer":"This data was produced from the CoinDesk Bitcoin Price Index (USD). Non-USD currency data converted using hourly conversion rate from openexchangerates.org","chartName":"Bitcoin","bpi":{"USD":{"code":"USD","symbol":"&#36;","rate":"63,627.977","description":"United States Dollar","rate_float":63627.9772},"GBP":{"code":"GBP","symbol":"&pound;","rate":"51,151.294","description":"British Pound Sterling","rate_float":51151.2944},"EUR":{"code":"EUR","symbol":"&euro;","rate":"59,780.266","description":"Euro","rate_float":59780.2662},"CNY":{"code":"CNY","symbol":"&yen;","rate":"460,558.388","description":"Chinese Yuan","rate_float":460558.3875}}}