{"time":{"updated":"Jan 14, 2025 14:44:27 UTC","updatedISO":"2025-01-14T14:44:27+00:00","updateduk":"Jan 14, 2025 at 14:44 GMT"},"disclaimer":"This data was produced from the CoinDesk Bitcoin Price Index (USD). Non-USD currency data converted using hourly conversion rate from openexchangerates.org","chartName":"Bitcoin","bpi":{"USD":{"code":"USD","symbol":"&#36;","rate":"97,931.325","description":"United States Dollar","rate_float":97931.3251},"GBP":{"code":"GBP","symbol":"&pound;","rate":"78,107.577","description":"British Pound Sterling","rate_float":78107.5766},"EUR":{"code":"EUR","symbol":"&euro;","rate":"94,183.885","description":"Euro","rate_float":94183.885},"CNY":{"code":"CNY","symbol":"&yen;","rate":"717,630.958","description":"Chinese Yuan","rate_float":717630.9575}}}