{"time":{"updated":"Aug 30, 2024 03:39:01 UTC","updatedISO":"2024-08-30T03:39:01+00:00","updateduk":"Aug 30, 2024 at 04:39 BST"},"disclaimer":"This data was produced from the CoinDesk Bitcoin Price Index (USD). Non-USD currency data converted using hourly conversion rate from openexchangerates.org","chartName":"Bitcoin","bpi":{"USD":{"code":"USD","symbol":"&#36;","rate":"59,032.052","description":"United States Dollar","rate_float":59032.0516},"GBP":{"code":"GBP","symbol":"&pound;","rate":"44,847.476","description":"British Pound Sterling","rate_float":44847.4761},"EUR":{"code":"EUR","symbol":"&euro;","rate":"53,315.919","description":"Euro","rate_float":53315.919},"CNY":{"code":"CNY","symbol":"&yen;","rate":"418,743.858","description":"Chinese Yuan","rate_float":418743.8583}}}