{"time":{"updated":"Jun 15, 2024 07:53:10 UTC","updatedISO":"2024-06-15T07:53:10+00:00","updateduk":"Jun 15, 2024 at 08:53 BST"},"disclaimer":"This data was produced from the CoinDesk Bitcoin Price Index (USD). Non-USD currency data converted using hourly conversion rate from openexchangerates.org","chartName":"Bitcoin","bpi":{"USD":{"code":"USD","symbol":"&#36;","rate":"66,168.151","description":"United States Dollar","rate_float":66168.1514},"GBP":{"code":"GBP","symbol":"&pound;","rate":"52,211.899","description":"British Pound Sterling","rate_float":52211.8987},"EUR":{"code":"EUR","symbol":"&euro;","rate":"61,738.392","description":"Euro","rate_float":61738.3922},"CNY":{"code":"CNY","symbol":"&yen;","rate":"480,036.705","description":"Chinese Yuan","rate_float":480036.7048}}}