{"time":{"updated":"Jan 28, 2025 16:45:05 UTC","updatedISO":"2025-01-28T16:45:05+00:00","updateduk":"Jan 28, 2025 at 16:45 GMT"},"disclaimer":"This data was produced from the CoinDesk Bitcoin Price Index (USD). Non-USD currency data converted using hourly conversion rate from openexchangerates.org","chartName":"Bitcoin","bpi":{"USD":{"code":"USD","symbol":"&#36;","rate":"102,706.368","description":"United States Dollar","rate_float":102706.3684},"GBP":{"code":"GBP","symbol":"&pound;","rate":"82,482.149","description":"British Pound Sterling","rate_float":82482.1493},"EUR":{"code":"EUR","symbol":"&euro;","rate":"98,195.197","description":"Euro","rate_float":98195.1966},"CNY":{"code":"CNY","symbol":"&yen;","rate":"746,336.367","description":"Chinese Yuan","rate_float":746336.3674}}}