{"time":{"updated":"Jun 8, 2024 02:48:20 UTC","updatedISO":"2024-06-08T02:48:20+00:00","updateduk":"Jun 8, 2024 at 03:48 BST"},"disclaimer":"This data was produced from the CoinDesk Bitcoin Price Index (USD). Non-USD currency data converted using hourly conversion rate from openexchangerates.org","chartName":"Bitcoin","bpi":{"USD":{"code":"USD","symbol":"&#36;","rate":"69,532.095","description":"United States Dollar","rate_float":69532.0947},"GBP":{"code":"GBP","symbol":"&pound;","rate":"54,629.211","description":"British Pound Sterling","rate_float":54629.2113},"EUR":{"code":"EUR","symbol":"&euro;","rate":"64,338.047","description":"Euro","rate_float":64338.0473},"CNY":{"code":"CNY","symbol":"&yen;","rate":"503,871.278","description":"Chinese Yuan","rate_float":503871.2778}}}