{"time":{"updated":"Jan 27, 2025 04:56:06 UTC","updatedISO":"2025-01-27T04:56:06+00:00","updateduk":"Jan 27, 2025 at 04:56 GMT"},"disclaimer":"This data was produced from the CoinDesk Bitcoin Price Index (USD). Non-USD currency data converted using hourly conversion rate from openexchangerates.org","chartName":"Bitcoin","bpi":{"USD":{"code":"USD","symbol":"&#36;","rate":"99,844.354","description":"United States Dollar","rate_float":99844.3536},"GBP":{"code":"GBP","symbol":"&pound;","rate":"79,633.36","description":"British Pound Sterling","rate_float":79633.3603},"EUR":{"code":"EUR","symbol":"&euro;","rate":"96,023.71","description":"Euro","rate_float":96023.7096},"CNY":{"code":"CNY","symbol":"&yen;","rate":"731,649.439","description":"Chinese Yuan","rate_float":731649.4387}}}