{"time":{"updated":"Jan 2, 2025 04:55:39 UTC","updatedISO":"2025-01-02T04:55:39+00:00","updateduk":"Jan 2, 2025 at 04:55 GMT"},"disclaimer":"This data was produced from the CoinDesk Bitcoin Price Index (USD). Non-USD currency data converted using hourly conversion rate from openexchangerates.org","chartName":"Bitcoin","bpi":{"USD":{"code":"USD","symbol":"&#36;","rate":"96,086.542","description":"United States Dollar","rate_float":96086.5421},"GBP":{"code":"GBP","symbol":"&pound;","rate":"76,627.096","description":"British Pound Sterling","rate_float":76627.0956},"EUR":{"code":"EUR","symbol":"&euro;","rate":"92,182.642","description":"Euro","rate_float":92182.642},"CNY":{"code":"CNY","symbol":"&yen;","rate":"701,297.236","description":"Chinese Yuan","rate_float":701297.2361}}}