{"time":{"updated":"Jan 18, 2025 03:27:19 UTC","updatedISO":"2025-01-18T03:27:19+00:00","updateduk":"Jan 18, 2025 at 03:27 GMT"},"disclaimer":"This data was produced from the CoinDesk Bitcoin Price Index (USD). Non-USD currency data converted using hourly conversion rate from openexchangerates.org","chartName":"Bitcoin","bpi":{"USD":{"code":"USD","symbol":"&#36;","rate":"104,979.972","description":"United States Dollar","rate_float":104979.9721},"GBP":{"code":"GBP","symbol":"&pound;","rate":"83,729.401","description":"British Pound Sterling","rate_float":83729.4012},"EUR":{"code":"EUR","symbol":"&euro;","rate":"100,962.808","description":"Euro","rate_float":100962.8084},"CNY":{"code":"CNY","symbol":"&yen;","rate":"769,282.737","description":"Chinese Yuan","rate_float":769282.7372}}}