{"time":{"updated":"Oct 15, 2024 18:50:02 UTC","updatedISO":"2024-10-15T18:50:02+00:00","updateduk":"Oct 15, 2024 at 19:50 BST"},"disclaimer":"This data was produced from the CoinDesk Bitcoin Price Index (USD). Non-USD currency data converted using hourly conversion rate from openexchangerates.org","chartName":"Bitcoin","bpi":{"USD":{"code":"USD","symbol":"&#36;","rate":"66,896.131","description":"United States Dollar","rate_float":66896.1309},"GBP":{"code":"GBP","symbol":"&pound;","rate":"51,206.446","description":"British Pound Sterling","rate_float":51206.4462},"EUR":{"code":"EUR","symbol":"&euro;","rate":"61,456.405","description":"Euro","rate_float":61456.4052},"CNY":{"code":"CNY","symbol":"&yen;","rate":"476,273.694","description":"Chinese Yuan","rate_float":476273.6939}}}