{"time":{"updated":"Sep 13, 2024 18:59:34 UTC","updatedISO":"2024-09-13T18:59:34+00:00","updateduk":"Sep 13, 2024 at 19:59 BST"},"disclaimer":"This data was produced from the CoinDesk Bitcoin Price Index (USD). Non-USD currency data converted using hourly conversion rate from openexchangerates.org","chartName":"Bitcoin","bpi":{"USD":{"code":"USD","symbol":"&#36;","rate":"59,784.782","description":"United States Dollar","rate_float":59784.782},"GBP":{"code":"GBP","symbol":"&pound;","rate":"45,548.292","description":"British Pound Sterling","rate_float":45548.2917},"EUR":{"code":"EUR","symbol":"&euro;","rate":"53,949.847","description":"Euro","rate_float":53949.8471},"CNY":{"code":"CNY","symbol":"&yen;","rate":"424,083.352","description":"Chinese Yuan","rate_float":424083.3515}}}