{"time":{"updated":"Aug 15, 2022 11:42:00 UTC","updatedISO":"2022-08-15T11:42:00+00:00","updateduk":"Aug 15, 2022 at 12:42 BST"},"disclaimer":"This data was produced from the CoinDesk Bitcoin Price Index (USD). Non-USD currency data converted using hourly conversion rate from openexchangerates.org","chartName":"Bitcoin","bpi":{"USD":{"code":"USD","symbol":"&#36;","rate":"24,108.8840","description":"United States Dollar","rate_float":24108.884},"GBP":{"code":"GBP","symbol":"&pound;","rate":"20,145.1906","description":"British Pound Sterling","rate_float":20145.1906},"EUR":{"code":"EUR","symbol":"&euro;","rate":"23,485.5729","description":"Euro","rate_float":23485.5729},"CNY":{"code":"CNY","symbol":"&yen;","rate":"40,202.5000","description":"Chinese Yuan","rate_float":40202.5}}}